dockerfactory/__init__.py
dockerfactory/__main__.py
dockerfactory/config.py
dockerfactory-0.1.dist-info/DESCRIPTION.rst
dockerfactory-0.1.dist-info/METADATA
dockerfactory-0.1.dist-info/RECORD
dockerfactory-0.1.dist-info/WHEEL
dockerfactory-0.1.dist-info/entry_points.txt
dockerfactory-0.1.dist-info/metadata.json
dockerfactory-0.1.dist-info/top_level.txt
