Metadata-Version: 2.0
Name: dockerfactory
Version: 0.1
Summary: Control the context of your docker builds.
Home-page: https://github.com/six8/dockerfactory
Author: Michael Thornton
Author-email: six8@devdetails.com
License: MIT
Platform: UNKNOWN
Requires-Dist: click (>=6.2,<7)
Requires-Dist: pyyaml (>=3.11,<4)
Requires-Dist: schematics (>=1.1.1,<2)
